openx12/__init__.py
openx12/__main__.py
openx12/cli.py
openx12/x835.py
openx12/x837i.py
openx12/x837p.py
openx12-0.2.1.dist-info/METADATA
openx12-0.2.1.dist-info/WHEEL
openx12-0.2.1.dist-info/entry_points.txt
openx12-0.2.1.dist-info/licenses/LICENSE
openx12-0.2.1.dist-info/RECORD
