Metadata-Version: 2.4
Name: openx12
Version: 0.2.1
Summary: Python library for parsing X12 healthcare EDI files (835, 837P, 837I)
Project-URL: Homepage, https://github.com/josephbiagio/openx12
Project-URL: Repository, https://github.com/josephbiagio/openx12
Project-URL: Issues, https://github.com/josephbiagio/openx12/issues
Author: Joseph Biagio
License-Expression: MIT
License-File: LICENSE
Keywords: 835,837,claims,edi,era,healthcare,hipaa,x12
Classifier: Development Status :: 3 - Alpha
Classifier: Intended Audience :: Developers
Classifier: Intended Audience :: Healthcare Industry
Classifier: License :: OSI Approved :: MIT License
Classifier: Programming Language :: Python :: 3
Classifier: Programming Language :: Python :: 3.10
Classifier: Programming Language :: Python :: 3.11
Classifier: Programming Language :: Python :: 3.12
Classifier: Topic :: Software Development :: Libraries :: Python Modules
Requires-Python: >=3.10
Provides-Extra: dev
Requires-Dist: pytest>=7.0; extra == 'dev'
